{
    "coverage diff": [
        -1.29,
        -1.92,
        -2.39,
        -2.42,
        -1.48,
        -0.19,
        1.07,
        1.05,
        1.0,
        0.18,
        1.27,
        -0.82,
        0.15,
        0.67,
        1.11,
        1.02,
        1.45
    ],
    "coverage diff total": 19.49,
    "coverage estimated": [
        -2.29,
        -2.92,
        -3.39,
        -3.42,
        -2.48,
        -1.19,
        0.07,
        0.05,
        0.0,
        -0.82,
        0.27,
        -1.82,
        -0.85,
        -0.33,
        0.11,
        0.02,
        0.45
    ],
    "coverage estimated total": -18.5436746373859,
    "coverage ground truth": [
        -1.0,
        -1.0,
        -1.0,
        -1.0,
        -1.0,
        -1.0,
        -1.0,
        -1.0,
        -1.0,
        -1.0,
        -1.0,
        -1.0,
        -1.0,
        -1.0,
        -1.0,
        -1.0,
        -1.0
    ],
    "coverage ground truth total": -1,
    "sol": [
        1.0,
        1.0,
        1.0,
        1.0,
        1.0,
        1.0,
        1.0,
        1.0,
        1.0,
        1.0,
        1.0,
        1.0,
        1.0,
        1.0,
        1.0,
        1.0,
        0.0
    ]
}